{"version":1,"resource":"file:///c%3A/Users/YEP/Desktop/gestion-ista/app/Http/Controllers/Api/IstaController.php","entries":[{"id":"U28g.php","timestamp":1769534940293},{"id":"FNrO.php","source":"undoRedo.source","timestamp":1769534944961},{"id":"q7Bc.php","timestamp":1769534964768},{"id":"7ntb.php","timestamp":1769535162056},{"id":"2GzZ.php","timestamp":1769536256364},{"id":"0NIN.php","timestamp":1769536268202},{"id":"Gthn.php","source":"undoRedo.source","timestamp":1769536269715},{"id":"bNx3.php","timestamp":1769536664623},{"id":"MYQx.php","timestamp":1769538193461},{"id":"mZ5j.php","timestamp":1769538829800},{"id":"ROWK.php","timestamp":1769540286214},{"id":"ZFEa.php","timestamp":1769540533407},{"id":"KTu8.php","timestamp":1769545358173},{"id":"wUtQ.php","timestamp":1769550087935},{"id":"Ewyj.php","source":"undoRedo.source","timestamp":1769550092104},{"id":"J8qx.php","timestamp":1769550270940},{"id":"HYdd.php","timestamp":1769551854581},{"id":"ZdRw.php","timestamp":1769552225703},{"id":"DDwd.php","source":"undoRedo.source","timestamp":1769552386936},{"id":"1A37.php","timestamp":1769553313929},{"id":"za9X.php","timestamp":1769553515360},{"id":"vvSI.php","source":"undoRedo.source","timestamp":1769553598418},{"id":"tjgN.php","timestamp":1769554101148},{"id":"Jfbr.php","timestamp":1769554620326},{"id":"V5dU.php","timestamp":1769555241356},{"id":"8WfH.php","source":"undoRedo.source","timestamp":1769555243012},{"id":"VbOx.php","timestamp":1769555249759},{"id":"mCvD.php","source":"undoRedo.source","timestamp":1769555252616},{"id":"R9Yt.php","timestamp":1769555256315},{"id":"oexK.php","timestamp":1769555269482},{"id":"VJms.php","source":"undoRedo.source","timestamp":1769555273888},{"id":"KaqY.php","timestamp":1769555277707},{"id":"ObUv.php","timestamp":1769555288675},{"id":"xw5f.php","timestamp":1769555362537},{"id":"24h7.php","timestamp":1769555640311},{"id":"JZv0.php","timestamp":1769557179215},{"id":"odNH.php","source":"undoRedo.source","timestamp":1769557183099},{"id":"vno0.php","timestamp":1769557201093},{"id":"qrRc.php","timestamp":1769560577328},{"id":"3VkS.php","timestamp":1769561894555},{"id":"s9ac.php","timestamp":1769598902555},{"id":"KHQR.php","timestamp":1769599940305},{"id":"ys2T.php","timestamp":1769600106850},{"id":"5YGL.php","timestamp":1769600413490},{"id":"3SQ1.php","timestamp":1769608077952},{"id":"kjEn.php","timestamp":1769608284373},{"id":"xkiv.php","timestamp":1769609431675},{"id":"Rq3n.php","timestamp":1769610139409},{"id":"v3gh.php","timestamp":1769612892135},{"id":"6v9z.php","timestamp":1769699260595}]}